ipyvtk_simple/__init__.py
ipyvtk_simple/_version.py
ipyvtk_simple/constants.py
ipyvtk_simple/throttler.py
ipyvtk_simple/viewer.py
ipyvtk_simple-0.1.4.dist-info/LICENSE
ipyvtk_simple-0.1.4.dist-info/METADATA
ipyvtk_simple-0.1.4.dist-info/WHEEL
ipyvtk_simple-0.1.4.dist-info/top_level.txt
ipyvtk_simple-0.1.4.dist-info/RECORD
